listdbm/__init__.py
listdbm-0.0.3.dist-info/METADATA
listdbm-0.0.3.dist-info/WHEEL
listdbm-0.0.3.dist-info/top_level.txt
listdbm-0.0.3.dist-info/RECORD
