Metadata-Version: 2.1
Name: listdbm
Version: 0.0.3
Summary: helps you manage databases using lists
Author: Monil Darediya
Author-email: <monildarediya1@gmail.com>
Keywords: python,database,manage,db,list
Classifier: Development Status :: 3 - Alpha
Classifier: Intended Audience :: Developers
Classifier: Programming Language :: Python :: 3
Classifier: Operating System :: Unix
Classifier: Operating System :: MacOS :: MacOS X
Classifier: Operating System :: Microsoft :: Windows
